.VERSION
AUTHORS.rst
CONTRIBUTING.rst
HISTORY.rst
LICENSE
MANIFEST.in
Pipfile
Pipfile.lock
README.rst
USAGE.rst
dev-requirements.txt
requirements.txt
setup.cfg
setup.py
docs/Makefile
docs/authors.rst
docs/conf.py
docs/contributing.rst
docs/history.rst
docs/index.rst
docs/installation.rst
docs/readme.rst
docs/usage.rst
ynabinterfaceslib/.VERSION
ynabinterfaceslib/AUTHORS.rst
ynabinterfaceslib/CONTRIBUTING.rst
ynabinterfaceslib/HISTORY.rst
ynabinterfaceslib/LICENSE
ynabinterfaceslib/Pipfile
ynabinterfaceslib/Pipfile.lock
ynabinterfaceslib/README.rst
ynabinterfaceslib/USAGE.rst
ynabinterfaceslib/__init__.py
ynabinterfaceslib/_version.py
ynabinterfaceslib/dev-requirements.txt
ynabinterfaceslib/requirements.txt
ynabinterfaceslib/ynabinterfaceslib.py
ynabinterfaceslib/ynabinterfaceslibexceptions.py
ynabinterfaceslib.egg-info/PKG-INFO
ynabinterfaceslib.egg-info/SOURCES.txt
ynabinterfaceslib.egg-info/dependency_links.txt
ynabinterfaceslib.egg-info/not-zip-safe
ynabinterfaceslib.egg-info/requires.txt
ynabinterfaceslib.egg-info/top_level.txt