Metadata-Version: 1.1
Name: ynabinterfaceslib
Version: 1.0.0
Summary: A library implementing interfaces for institution (banks, other organizations) integrations to YNAB
Home-page: https://github.com/costastf/ynabinterfaceslib
Author: Costas Tyfoxylos
Author-email: costas.tyf@gmail.com
License: MIT
Keywords: ynabinterfaceslib
Platform: UNKNOWN
Classifier: Development Status :: 4 - Beta
Classifier: Intended Audience :: Developers
Classifier: License :: OSI Approved :: MIT License
Classifier: Natural Language :: English
Classifier: Programming Language :: Python :: 3.7
